configs
rst_parser
