Metadata-Version: 2.1
Name: rst-parser
Version: 0.1.3
Summary: A package for RST parsing
Home-page: https://github.com/JinfenLi/rst_parser
Author: Jinfen Li
Author-email: jli284@syr.edu
License: MIT
Classifier: Programming Language :: Python :: 3
Classifier: License :: OSI Approved :: Apache Software License
Classifier: Programming Language :: Python :: 3.9
